trvae/__init__.py
trvae/data.py
trvae/metrics.py
trvae/plotting.py
trvae/utils.py
trvae/models/__init__.py
trvae/models/_activations.py
trvae/models/_dctrvae.py
trvae/models/_layers.py
trvae/models/_losses.py
trvae/models/_trvae.py
trvae/models/_utils.py
trVAE-1.1.2.dist-info/LICENSE
trVAE-1.1.2.dist-info/METADATA
trVAE-1.1.2.dist-info/WHEEL
trVAE-1.1.2.dist-info/top_level.txt
trVAE-1.1.2.dist-info/RECORD
