Metadata-Version: 2.1
Name: trVAE
Version: 1.1.2
Summary: Condition out-of-sample prediction
Home-page: https://github.com/theislab/trvae
Author: Mohsen Naghipourfar, Mohammad Lotfollahi
Author-email: mohsen.naghipourfar@gmail.com, Mohammad.lotfollahi@helmholtz-muenchen.de
License: MIT
Platform: UNKNOWN
Classifier: Programming Language :: Python :: 3.6
Classifier: Programming Language :: Python :: 3.7
Classifier: Environment :: Console
Classifier: Framework :: Jupyter
Classifier: Intended Audience :: Developers
Classifier: Intended Audience :: Science/Research
Classifier: License :: OSI Approved :: MIT License
Classifier: Natural Language :: English
Classifier: Operating System :: MacOS :: MacOS X
Classifier: Operating System :: Microsoft :: Windows
Classifier: Operating System :: POSIX :: Linux
Requires-Dist: anndata
Requires-Dist: scanpy
Requires-Dist: adjustText
Requires-Dist: tensorflow (==1.15.2)
Requires-Dist: numpy
Requires-Dist: scipy
Requires-Dist: pandas
Requires-Dist: keras (==2.2.4)
Requires-Dist: matplotlib
Requires-Dist: seaborn
